fs2/__init__.py
fs2/_tools.py
fs2/_version.py
fs2/_words2lines.py
fs2/cat.py
fs2/cp.py
fs2/dl.py
fs2/fs2.py
fs2/info.py
fs2/ls.py
fs2/mkdir.py
fs2/mv.py
fs2/rm.py
fs2/rmdir.py
fs2/tree.py
fs2/up.py
fs2-0.1.dist-info/LICENSE
fs2-0.1.dist-info/METADATA
fs2-0.1.dist-info/WHEEL
fs2-0.1.dist-info/entry_points.txt
fs2-0.1.dist-info/top_level.txt
fs2-0.1.dist-info/RECORD
