Metadata-Version: 2.1
Name: fs2
Version: 0.1
Summary: A cmd tool based on pyfilesystem2 lib
Home-page: https://github.com/pythonwood/fs2
Author: pythonwood
Author-email: 58223837@qq.com
License: MIT
Platform: any
Requires-Python: >=3.6
Requires-Dist: setuptools
Requires-Dist: click
Requires-Dist: fs
Requires-Dist: typing (~=3.6) ; python_version < '3.6'
